{
  "theme" : {
    "base" : "default"
  },
  "context" : "/appmgt",
  "cloudMgtContext" : "/cloudmgt",
  "dashboardContext" : "/dashboard",
  "recentAPIsCount" : 5,
  "topRatedCount" : 5,
  "defaultUser" : {
    "username" : "admin",
    "password" : "admin"
  },
  "distributable" : true,
  "ssoConfiguration" : {
    "issuer" : "appmgt",
    "identityProviderURL" : "https://localhost:9444/samlsso",
    "keyStorePassword": "wso2carbon",
    "identityAlias" : "wso2carbon",
    "keyStoreName" : "/home/kasuns/Documents/cloud-setup/setup/wso2as-5.2.1/repository/resources/security/wso2carbon.jks"
  }
}
